druida/Stack.py
druida/__init__.py
druida/setup.py
druida/DataManager/__init__.py
druida/DataManager/datamanager.py
druida/atom/__init__.py
druida/atom/builder.py
druida/atom/notes.txt
druida/surface/__init__.py
druida/surface/metasurface.py
druida/tools/__init__.py
druida/tools/toolkit.py
druida/tools/unetAttention.py
druida/tools/utils.py
druida-0.0.86.dist-info/METADATA
druida-0.0.86.dist-info/WHEEL
druida-0.0.86.dist-info/RECORD
