Metadata-Version: 2.4
Name: druida
Version: 0.0.86
Summary: Metasurface-design artificial intelligence
Project-URL: Homepage, https://github.com/Jorgecardenas1/druida_proof_of_concept
Author-email: Jorge Cardenas <jorge.cardenas.l@mail.pucv.cl>
Classifier: License :: OSI Approved :: MIT License
Classifier: Operating System :: OS Independent
Classifier: Programming Language :: Python :: 3
Requires-Python: >=3.7
Requires-Dist: ezdxf
Requires-Dist: imutils
Requires-Dist: matplotlib
Requires-Dist: numpy<=1.24.3
Requires-Dist: opencv-python
Requires-Dist: pandas~=2.1.0
Requires-Dist: pillow
Requires-Dist: scikit-learn
Requires-Dist: tensorflow
Requires-Dist: torch
Requires-Dist: torchsummary
Requires-Dist: torchvision
Requires-Dist: tqdm
Requires-Dist: transformers
Requires-Dist: wheel
